mcp_server_docker/__init__.py
mcp_server_docker/input_schemas.py
mcp_server_docker/output_schemas.py
mcp_server_docker/server.py
mcp_server_docker/settings.py
mseep_mcp_server_docker-0.2.2.dist-info/licenses/LICENSE
mseep_mcp_server_docker-0.2.2.dist-info/METADATA
mseep_mcp_server_docker-0.2.2.dist-info/WHEEL
mseep_mcp_server_docker-0.2.2.dist-info/entry_points.txt
mseep_mcp_server_docker-0.2.2.dist-info/top_level.txt
mseep_mcp_server_docker-0.2.2.dist-info/RECORD
