Metadata-Version: 2.4
Name: mseep-mcp-server-docker
Version: 0.2.2
Summary: A Docker MCP Server
Author-email: mseep <support@skydeck.ai>
License:                     GNU GENERAL PUBLIC LICENSE
Project-URL: Repository, https://github.com/ckreiling/mcp-server-docker
Project-URL: Issues, https://github.com/ckreiling/mcp-server-docker/issues
Keywords: docker,mcp,server
Classifier: Development Status :: 4 - Beta
Classifier: Programming Language :: Python :: 3.12
Requires-Python: >=3.12
License-File: LICENSE
Requires-Dist: docker>=7.1.0
Requires-Dist: mcp<2.0,>=1.1.0
Requires-Dist: paramiko<4.0,>=3.5.1
Requires-Dist: pydantic>=2.10.3
Requires-Dist: pydantic-settings>=2.6.1
Dynamic: license-file
